rdoclient_py3/__init__.py
rdoclient_py3/rdoclient.py
rdoclient_py3-2.0.6.dist-info/DESCRIPTION.rst
rdoclient_py3-2.0.6.dist-info/METADATA
rdoclient_py3-2.0.6.dist-info/RECORD
rdoclient_py3-2.0.6.dist-info/WHEEL
rdoclient_py3-2.0.6.dist-info/metadata.json
rdoclient_py3-2.0.6.dist-info/top_level.txt
