Metadata-Version: 2.0
Name: rdoclient-py3
Version: 2.0.6
Summary: RANDOM.ORG JSON-RPC API (Release 2) Python 3 implementation.
Home-page: https://github.com/nicorellius/json-rpc-python3
Author: RANDOM.ORG (original library), nicorellius (Python 3 implementation)
Author-email: nicorellius@protonmail.com
License: MIT
Keywords: RANDOM.ORG random client implementation
Platform: UNKNOWN
Classifier: Development Status :: 5 - Production/Stable
Classifier: Intended Audience :: Developers
Classifier: License :: OSI Approved :: MIT License
Classifier: Programming Language :: Python :: 3
Classifier: Programming Language :: Python :: 3.2
Classifier: Programming Language :: Python :: 3.3
Classifier: Programming Language :: Python :: 3.4
Classifier: Programming Language :: Python :: 3.5
Classifier: Programming Language :: Python :: 3.6
Classifier: Topic :: Software Development :: Libraries :: Python Modules
Requires-Python: >=3
Requires-Dist: pytest
Requires-Dist: requests
